lmlog/__init__.py
lmlog/async_processing.py
lmlog/backends.py
lmlog/config.py
lmlog/decorators.py
lmlog/logger.py
lmlog/otel_integration.py
lmlog/pools.py
lmlog/sampling.py
lmlog/serializers.py
lmlog-0.3.0.dist-info/METADATA
lmlog-0.3.0.dist-info/WHEEL
lmlog-0.3.0.dist-info/licenses/LICENSE
lmlog-0.3.0.dist-info/RECORD
