Metadata-Version: 2.4
Name: lmlog
Version: 0.3.0
Summary: LLM-optimized logging library for Python applications
Project-URL: Homepage, https://github.com/username/lmlog
Project-URL: Documentation, https://github.com/username/lmlog#readme
Project-URL: Repository, https://github.com/username/lmlog.git
Project-URL: Issues, https://github.com/username/lmlog/issues
Author-email: LMLog Team <team@lmlog.dev>
License: MIT
License-File: LICENSE
Keywords: debugging,json,llm,logging,structured
Classifier: Development Status :: 4 - Beta
Classifier: Intended Audience :: Developers
Classifier: License :: OSI Approved :: MIT License
Classifier: Programming Language :: Python :: 3
Classifier: Programming Language :: Python :: 3.11
Classifier: Programming Language :: Python :: 3.12
Classifier: Programming Language :: Python :: 3.13
Classifier: Topic :: Software Development :: Debuggers
Classifier: Topic :: System :: Logging
Requires-Python: >=3.11
Requires-Dist: msgspec>=0.18.0
Requires-Dist: opentelemetry-api>=1.20.0
Requires-Dist: orjson>=3.9.0
Provides-Extra: dev
Requires-Dist: black>=23.0.0; extra == 'dev'
Requires-Dist: pyrefly>=0.21.0; extra == 'dev'
Requires-Dist: pytest-asyncio>=0.21.0; extra == 'dev'
Requires-Dist: pytest-cov>=4.0.0; extra == 'dev'
Requires-Dist: pytest-xdist[psutil]>=3.7.0; extra == 'dev'
Requires-Dist: pytest>=7.0.0; extra == 'dev'
Requires-Dist: ruff>=0.1.0; extra == 'dev'
